onnxruntime_vitisai/__init__.py
onnxruntime_vitisai-0.0.2.dist-info/METADATA
onnxruntime_vitisai-0.0.2.dist-info/WHEEL
onnxruntime_vitisai-0.0.2.dist-info/top_level.txt
onnxruntime_vitisai-0.0.2.dist-info/RECORD
