Metadata-Version: 2.4
Name: onnxruntime-vitisai
Version: 0.0.2
Summary: ONNX Runtime is a runtime accelerator for Machine Learning models
Author-email: AMD <support@amd.com>
License: MIT License
Project-URL: Homepage, https://onnxruntime.ai
Requires-Python: >=3.8
